mpaiexec/Iaes.py
mpaiexec/Icc.py
mpaiexec/Ides.py
mpaiexec/Idfhm.py
mpaiexec/Ihmacsha1.py
mpaiexec/Imc.py
mpaiexec/Imd5.py
mpaiexec/Ipc.py
mpaiexec/Irf.py
mpaiexec/Irsa.py
mpaiexec/Isc.py
mpaiexec/Issl.py
mpaiexec/Ivc.py
mpaiexec/Wasptojava_add.py
mpaiexec/Wresttoservlet_database.py
mpaiexec/Wsoaptojava_tempcon.py
mpaiexec/Wsoaptojsp_oneway.py
mpaiexec/Wsoaptoservlet_si.py
mpaiexec/Wwcfasynchronous.py
mpaiexec/Wwcftypical.py
mpaiexec/ins.py
mpaiexec-0.8.dist-info/METADATA
mpaiexec-0.8.dist-info/WHEEL
mpaiexec-0.8.dist-info/top_level.txt
mpaiexec-0.8.dist-info/RECORD
