Metadata-Version: 2.1
Name: mpaiexec
Version: 0.8
Summary: AIPackage
Home-page: https://github.com/mayurpunjabi/AIPackage
Author: Mayur Punjabi
Author-email: mayurpunjabi7@gmail.com
License: UNKNOWN
Platform: UNKNOWN
Classifier: Programming Language :: Python :: 3
Classifier: License :: OSI Approved :: MIT License
Classifier: Operating System :: OS Independent
